{
  "model_no": "LS-68RP-EZ",
  "product_name": "EZ 플러그 랜툴 (PASS 콘넥터 전용 EZ 플러그 랜툴)",
  "category": [
    "랜케이블",
    "커넥터"
  ],
  "key_features": [
    "휴대가 가능하여 작업 효율을 높일 수 있는 휴대용 랜툴",
    "전화선(6P6C)과 랜케이블(8P8C) 동시 작업 가능",
    "케이블 탈피와 컷팅을 하나의 툴로 손쉽게 처리 가능",
    "기어 형식 구조로 적은 힘으로도 작업 가능",
    "PASS 콘넥터 압착과 통과된 케이블 절단을 동시에 한 번에 처리 가능",
    "PASS 콘넥터 전용이지만 일반 콘넥터에서도 사용 가능"
  ],
  "specifications": {
    "모델명": "LS-68RP-EZ",
    "브랜드": "LANStar",
    "제조사/수입사": "라인업시스템(주)",
    "제조국/원산지": "중국 (China)",
    "인증번호": "해당없음",
    "지원 커넥터 규격": "6P6C, 8P8C",
    "제품 크기": "22cm x 6cm x 10.6cm (참고: 세부 치수 5cm, 5cm, 6cm, 10.6cm, 17cm, 22cm 표기)",
    "보험": "현대해상화재 생산물배상책임보험 1억원 가입",
    "환경 인증": "RoHS COMPLIANT",
    "안전 인증": "KC (국내), FCC (미국), CE (유럽연합 및 유럽자유무역국가)",
    "AS 소비자상담": "랜스타 A/S센터 www.LANstar.co.kr"
  },
  "compatibility": [
    "UTP PASS 콘넥터 CAT.5E (모델명: LSN-5EPASS-UTP, 상품번호: 40662)",
    "UTP PASS 콘넥터 CAT.6 (모델명: LSN-6PASS-UTP, 상품번호: 40663)",
    "UTP PASS 콘넥터 CAT.7 (모델명: LS-PASS-7UTP, 상품번호: 20275)",
    "STP PASS 콘넥터 CAT.5E (모델명: LSN-PASS-5ESTP, 상품번호: 40679)",
    "STP PASS 콘넥터 CAT.6 (모델명: LSN-6PASS-STP, 상품번호: 20147)",
    "STP PASS 콘넥터 CAT.7 (모델명: LS-PASS-7STP, 상품번호: 20276)",
    "랜케이블 CAT.5 / CAT.6 / CAT.7",
    "전화선 RJ12 (6P6C)",
    "일반 콘넥터 (8P8C)"
  ],
  "package_contents": [
    "LS-68RP-EZ EZ 플러그 랜툴 본체 1개"
  ],
  "usage_instructions": "1. 작업에 필요한 랜선을 준비한 뒤 LS-68RP-EZ의 탈피 부분을 이용해 케이블 피복을 벗긴다. 2. 피복을 벗긴 케이블을 랜 케이블 핀 배열도(다이렉트: 568B-568B / 크로스: 568B-568A)에 맞춰 PASS 콘넥터에 연결한다. 3. 케이블을 연결한 콘넥터를 LS-68RP-EZ 툴에 삽입하여 압착시킨다. 4. 압착과 동시에 PASS 콘넥터를 통과한 케이블이 자동 절단되어 작업이 완료된다.",
  "cautions": [
    "제조사의 사정에 따라 제품의 색상 및 형태 등의 사양은 예고 없이 변경될 수 있음",
    "RoHS 지침 준수 제품으로 납, 수은, 카드뮴 등 중금속 사용 제한 기준을 만족함",
    "본 제품에 이상이 있으면 공정거래위원회 고시 소비자 분쟁해결 기준에 따라 보상 가능",
    "라인업시스템(주)에서 제작한 상품과 콘텐츠를 당사의 동의 없이 무단 복제 및 이용 시 불이익을 당할 수 있음"
  ],
  "variants": [
    {
      "model_no": "LS-68RP-EZ",
      "품목코드": "NEO-LAN105",
      "품목명": "[LANstar] EZ플러그 랜툴 , EZ 관통형 콘넥터 전용 툴 [20188](50개)",
      "variant_suffix": "",
      "source": "excel"
    }
  ],
  "reviews": [
    {
      "source_model": "LS-68RP-EZ",
      "내용": "배송도 빠르고 랜툴도 좋네요."
    },
    {
      "source_model": "LS-68RP-EZ",
      "내용": "빠른배송 감사드립니다.",
      "관련내용": "항상 사용하는제품!"
    },
    {
      "source_model": "LS-68RP-EZ",
      "내용": "항상 사용하는제품!"
    },
    {
      "source_model": "LS-68RP-EZ",
      "내용": "맘에 들어요 일체로 선까지 잘려서 좋아요",
      "관련내용": "예상대로 마감도 좋고 품질도 좋네요. 눈에 띄는건 컷팅 날이 노출되지 않도록 안전 커버가 있다는게 인상적입니다. 많이 파세요!"
    },
    {
      "source_model": "LS-68RP-EZ",
      "내용": "예상대로 마감도 좋고 품질도 좋네요. 눈에 띄는건 컷팅 날이 노출되지 않도록 안전 커버가 있다는게 인상적입니다. 많이 파세요!"
    },
    {
      "source_model": "LS-68RP-EZ",
      "내용": "해외 현장에서 너무너무 잘사용 중입니다.",
      "관련내용": "빠른배송 고맙습니다"
    },
    {
      "source_model": "LS-68RP-EZ",
      "내용": "빠른배송 고맙습니다"
    },
    {
      "source_model": "LS-68RP-EZ",
      "내용": "빠른배송 감사합니다"
    },
    {
      "source_model": "LS-68RP-EZ",
      "내용": "빠른배송 감사합니다"
    },
    {
      "source_model": "LS-68RP-EZ",
      "내용": "매우 좋아요 잘 쓰고 있어요 !!",
      "관련내용": "빠른 배송 감사합니다.\n너무 좋네요 잘 쓸게요 !!"
    },
    {
      "source_model": "LS-68RP-EZ",
      "내용": "이상없이 잘쓰고있습니다"
    },
    {
      "source_model": "LS-68RP-EZ",
      "내용": "빠른배송 감사 합니다."
    },
    {
      "source_model": "LS-68RP-EZ",
      "내용": "빠른 배송 감사합니다.\n너무 좋네요 잘 쓸게요 !!"
    },
    {
      "source_model": "LS-68RP-EZ",
      "내용": "연결이 아주 잘되네요",
      "관련내용": "빠른배송 감사합니다 ^^"
    },
    {
      "source_model": "LS-68RP-EZ",
      "내용": "자주 사용하지 않아서 저렴한걸로 찾았는데 너무 잘되요"
    },
    {
      "source_model": "LS-68RP-EZ",
      "내용": "빠른배송 감사합니다 ^^"
    },
    {
      "source_model": "LS-68RP-EZ",
      "내용": "빠른배송 고맙습니다"
    },
    {
      "source_model": "LS-68RP-EZ",
      "내용": "마음에 듭니다 많이파세요",
      "관련내용": "마음에 듭니다 많이 파세요"
    },
    {
      "source_model": "LS-68RP-EZ",
      "내용": "마음에 듭니다 많이 파세요"
    },
    {
      "source_model": "LS-68RP-EZ",
      "내용": "잘 작동합니다 작업에 잘쓰고 있습니다."
    },
    {
      "source_model": "LS-68RP-EZ",
      "내용": "가성비 좋은 제품 잘 쓰겠습니다"
    },
    {
      "source_model": "LS-68RP-EZ",
      "내용": "관통형 랜선 작업할 때\n랜 커넥터 찝을 때\n앞의 선 까지 다 잘라주기 때문에\n사용시 매우 편리합니다",
      "관련내용": "피복 벗기는 기능도 있고,\n전선 절단하는 기능 등 이거 한 개로 대부분 다 해결할 수 있어서 좋습니다"
    },
    {
      "source_model": "LS-68RP-EZ",
      "내용": "포장이 잘되서 왔어요"
    },
    {
      "source_model": "LS-68RP-EZ",
      "내용": "인터넷이 빨라졌어요. 강추. 좋아요."
    },
    {
      "source_model": "LS-68RP-EZ",
      "내용": "피복 벗기는 기능도 있고,\n전선 절단하는 기능 등 이거 한 개로 대부분 다 해결할 수 있어서 좋습니다"
    },
    {
      "source_model": "LS-68RP-EZ",
      "내용": "만족도 5점을 주셨네요.\n어떤 점이 좋았나요?\n최소 10자 이상 입력해주세요."
    },
    {
      "source_model": "LS-68RP-EZ",
      "내용": "1. 배송이 빨라서 좋았습니다 하루만에옴\n\n2.  주문한 상품 포장이 잘되어 있었음\n\n3. 아주 아주 장문의 질문으로 판매자분을 매우매우 귀찮게 했음에도 상세하게 답변을 다해주심"
    },
    {
      "source_model": "LS-68RP-EZ",
      "내용": "튼튼하고 사용시 편리하고 좋습니다\n조잡할까봐 여러제품 중 고민 많이 하고 선택했는데 품질아 너무 만족합니다"
    },
    {
      "source_model": "LS-68RP-EZ",
      "내용": "기존제품과 다른게 기존제품에 칼날 하나 더 달려있을 뿐인데... 가격이 ㅎㄷㄷ",
      "관련내용": "기존 랜 툴에 칼날 하나 더 달린 느낌인데... 다른건 몰라도 완전히 접히지 않네요...^^;;;"
    },
    {
      "source_model": "LS-68RP-EZ",
      "내용": "가성비으로 너무 좋아요",
      "관련내용": "인식 잘되용!! 잘구입했어요"
    },
    {
      "source_model": "LS-68RP-EZ",
      "내용": "인식 잘되용!! 잘구입했어요"
    },
    {
      "source_model": "LS-68RP-EZ",
      "내용": "기존 랜 툴에 칼날 하나 더 달린 느낌인데... 다른건 몰라도 완전히 접히지 않네요...^^;;;"
    },
    {
      "source_model": "LS-68RP-EZ",
      "내용": "배송 빠르고 제품 이상 없네요!! 저렴한 제품인 만큼 큰기대는 안하시는게 좋으실듯 하네요!"
    },
    {
      "source_model": "LS-68RP-EZ",
      "내용": "설치 잘 하고 있습니다"
    },
    {
      "source_model": "LS-68RP-EZ",
      "내용": "통과형 콘넥터를 사용하고 있어서 구매했는데, 잘 찝어져서 좋아요."
    },
    {
      "source_model": "LS-68RP-EZ",
      "내용": "맘에들어요 매번시켜요"
    },
    {
      "source_model": "LS-68RP-EZ",
      "내용": "빠른 배송에 상담도 친절해요"
    },
    {
      "source_model": "LS-68RP-EZ",
      "내용": "좋습니다. 통과혀유과ㅠ같이ㅜ사야ㅜ합니다."
    },
    {
      "source_model": "LS-68RP-EZ",
      "내용": "빠른배송 감사합니다."
    }
  ],
  "qna": [
    {
      "source_model": "LS-68RP-EZ",
      "id": 222861307,
      "date": "2022-06-06 17:12",
      "answerDate": "2022-06-07 15:52",
      "user": "feud********",
      "productName": "랜스타 EZ플러그 랜툴 랜스타 콘넥터 전용 LS-68RP-EZ",
      "question": "ls-f7-utpd-20m 평면 랜케이블을 구입하여 커넥터를 잘라낸 뒤에 작은 구멍에 통과 시키고 다시 결합하려고 합니다 혹시 본 랜툴로 평면 케이블과 커넥터 결합이 가능한가요? 커넥터 추천도 부탁드립니다!",
      "answer": "안녕하세요 랜스타입니다.\n\n해당 케이블은 평면용 특수한 케이블과 커넥터로 제작되어 있어 호환이 어려울 수 있는 점 참고 부탁드리겠습니다.\n\n감사합니다."
    }
  ],
  "features": {
    "connectivity": {
      "input_signals": null,
      "output_signals": null,
      "directional": "N/A",
      "port_count": null
    },
    "power": {
      "power_mode": "N/A",
      "charging_support": null,
      "pd_watts": null
    },
    "form_physical": {
      "has_case": true,
      "material": null,
      "length_meters": null,
      "length_options_meters": null,
      "color_options": null
    },
    "certification": {
      "kc": true,
      "rohs": true,
      "iso9001": null,
      "fcc": true,
      "ce": true,
      "netflix": null
    },
    "audio_video": {
      "max_resolution": "N/A",
      "hdr_support": null,
      "hdcp_version": "N/A",
      "audio_pass": null
    },
    "control_switching": {
      "has_remote": null,
      "has_hotkey": null,
      "has_physical_button": null,
      "has_mouse_switching": null,
      "has_auto_scan": null,
      "has_app_control": null
    },
    "family": {
      "cat_category": null,
      "shielding": null,
      "conductor": null,
      "awg": null,
      "pair_count": null,
      "flame_rating": null,
      "poe_support": null
    }
  },
  "feature_evidence": {
    "form_physical.has_case": "휴대용 랜툴",
    "certification.kc": "KC (국내)",
    "certification.rohs": "RoHS COMPLIANT",
    "certification.fcc": "FCC (미국)",
    "certification.ce": "CE (유럽연합 및 유럽자유무역국가)"
  },
  "feature_extracted_at": "2026-04-23T03:08:26",
  "feature_schema_version": "1.0.0"
}